HDL/Sine_LUT.sv
//Sine LUT with Quarter Wave Symmetry logic

//May want to add parabolic interpolation if noise is an issue.

module SineLUT (
    input logic clk,
    input logic [8:0] addr_full,  // 9-bit full address (0-511)
    output logic signed [15:0] data_out  // Signed 16-bit sine value
);

    // Store only first quarter (0 to pi/2, 128 entries) //may need to convert to BRAM storage depending on LUT usage
    logic signed [15:0] sin_lut_quarter [0:127] = '{
        16'h0000, 16'h0192, 16'h0324, 16'h04B6, 16'h0648, 16'h07D9, 16'h096A, 16'h0AFB, 
        16'h0C8C, 16'h0E1C, 16'h0FAB, 16'h113A, 16'h12C8, 16'h1455, 16'h15E2, 16'h176E,
        16'h18F9, 16'h1A82, 16'h1C0B, 16'h1D93, 16'h1F1A, 16'h209F, 16'h2223, 16'h23A6,
        16'h2528, 16'h26A8, 16'h2826, 16'h29A3, 16'h2B1F, 16'h2C99, 16'h2E11, 16'h2F87,
        16'h30FB, 16'h326E, 16'h33DF, 16'h354D, 16'h36BA, 16'h3824, 16'h398C, 16'h3AF2,
        16'h3C56, 16'h3DB8, 16'h3F17, 16'h4073, 16'h41CE, 16'h4325, 16'h447A, 16'h45CD,
        16'h471C, 16'h4869, 16'h49B4, 16'h4AFB, 16'h4C3F, 16'h4D81, 16'h4EBF, 16'h4FFB,
        16'h5133, 16'h5268, 16'h539B, 16'h54C9, 16'h55F5, 16'h571D, 16'h5842, 16'h5964,
        16'h5A82, 16'h5B9C, 16'h5CB3, 16'h5DC7, 16'h5ED7, 16'h5FE3, 16'h60EB, 16'h61F0,
        16'h62F1, 16'h63EE, 16'h64E8, 16'h65DD, 16'h66CF, 16'h67BC, 16'h68A6, 16'h698B,
        16'h6A6D, 16'h6B4A, 16'h6C23, 16'h6CF8, 16'h6DC9, 16'h6E96, 16'h6F5E, 16'h7022,
        16'h70E2, 16'h719D, 16'h7254, 16'h7307, 16'h73B5, 16'h745F, 16'h7504, 16'h75A5,
        16'h7641, 16'h76D8, 16'h776B, 16'h77FA, 16'h7884, 16'h7909, 16'h7989, 16'h7A05,
        16'h7A7C, 16'h7AEE, 16'h7B5C, 16'h7BC5, 16'h7C29, 16'h7C88, 16'h7CE3, 16'h7D39,
        16'h7D89, 16'h7DD5, 16'h7E1D, 16'h7E5F, 16'h7E9C, 16'h7ED5, 16'h7F09, 16'h7F37,
        16'h7F61, 16'h7F86, 16'h7FA6, 16'h7FC1, 16'h7FD8, 16'h7FE9, 16'h7FF5, 16'h7FFD,
        16'h7FFF  
    };

    logic [6:0] addr_quarter;  // 7-bit quarter address (0-127)
    logic [1:0] quadrant;            // 0-3 based on MSB bits
    logic signed [15:0] lut_val;
    logic sign_flip;

    always_comb begin
        // Determine quadrant from addr_full[8:7]
        quadrant = addr_full[8:7];
        // assign quarter address based on quadrant
        unique case (quadrant)
            2'b00: begin  // Q1: direct
                addr_quarter = addr_full[6:0];
                sign_flip = 0;
            end
            2'b01: begin  // Q2: mirror of Q1
                addr_quarter = 127 - addr_full[6:0];
                sign_flip = 0;
            end
            2'b10: begin  // Q3: mirror + negate Q1
                addr_quarter = addr_full[6:0];
                sign_flip = 1;
            end
            2'b11: begin  // Q4: direct + negate Q1
                addr_quarter = 127 - addr_full[6:0];
                sign_flip = 1;
            end
        endcase
        // Lookup value from quarter sine LUT
        lut_val = sin_lut_quarter[addr_quarter];
    end

    always_ff @(posedge clk) begin
        if (sign_flip)
            data_out <= -lut_val;
        else
            data_out <= lut_val;
        
    end

endmodule

HDL/PhaseAccumulator.sv
//Phase Accumulator Module




module PhaseAccumulator #(

    parameter PHASE_WIDTH = 10;

)(
    input logic clk,
    input logic rst_active_high,
    input logic [PHASE_WIDTH - 1:0] freq_control_word,
    output logic [PHASE_WIDTH - 1:0] phase_accumulator_out
);

    logic [PHASE_WIDTH - 1:0] phase_accumulator_reg;

    always @(posedge clk or posedge rst_active_high) begin
        if (rst_active_high) begin
            phase_accumulator_reg <= 0;
        end else begin
            phase_accumulator_reg <= phase_accumulator_reg + freq_control_word;
        end
    end

    assign phase_accumulator_out = phase_accumulator_reg;


endmodule

HDL/DDS_Sine.sv
// DDS Sine Module

module DDS_Sine #(
    parameter int PHASE_WIDTH = 32,
    parameter int DATA_WIDTH  = 16
)(
    input  logic                         clk,
    input  logic                         rst_active_high,
    input  logic [PHASE_WIDTH-1:0]       freq_word,
    output logic [15:0]                  sine_out
);

    // Internal signals
    logic [PHASE_WIDTH-1:0]         phase_acc_out;
    logic [8:0]                     lut_addr;
    logic signed [15:0]             lut_data;        // output of SineLUT (signed 16-bit)
   -

    

    PhaseAccumulator #(
        .PHASE_WIDTH(PHASE_WIDTH)
    ) phase_acc_i (
        .clk(clk),
        .rst_active_high(rst_active_high),
        .freq_control_word(freq_word),
        .phase_accumulator_out(phase_acc_out)
    );

    
    // Use the top 9 bits of the phase accumulator as the LUT address

    assign lut_addr = phase_acc_out[PHASE_WIDTH-1 -: 9]; //-: counts down instead of +: that counts up 

    
    SineLUT SineLUT (
        .clk(clk),
        .addr_full(lut_addr),
        .data_out(lut_data)
    );

   
    // Register output on clock edge with synchronous active-high reset

    always_ff @(posedge clk or posedge rst_active_high) begin
        if (rst_active_high) begin
            sine_out <= '0;
        end else begin
            sine_out <= lut_data;
        end
    end

endmodule

spartan_tracker/spartan_tracker.srcs/sources_1/imports/HDL/DDS_Sine_tb.sv
`timescale 1ns / 1ps

module tb_DDS_Sine;
    parameter int PHASE_WIDTH = 32;
    parameter int DATA_WIDTH  = 16;
    parameter real CLK_PERIOD = 10.0; // 100 MHz clock

    logic                         clk;
    logic                         rst_active_high;
    logic [PHASE_WIDTH-1:0]       freq_word;
    logic signed [15:0]           sine_out;

    int waveform_file_handle;

    DDS_Sine #(
        .PHASE_WIDTH(PHASE_WIDTH),
        .DATA_WIDTH(DATA_WIDTH)
    ) dut (
        .clk(clk),
        .rst_active_high(rst_active_high),
        .freq_word(freq_word),
        .sine_out(sine_out)
    );

    always #(CLK_PERIOD/2) clk = ~clk;

    // Function to calculate frequency control word
    // freq_word = (desired_freq / clk_freq) * 2^PHASE_WIDTH
    function automatic logic [PHASE_WIDTH-1:0] calc_freq_word(real desired_freq_hz, real clk_freq_hz);
        real ratio;
        ratio = desired_freq_hz / clk_freq_hz;
        return longint'(ratio * (2.0 ** PHASE_WIDTH));
    endfunction

    // Initialize signals
    initial begin
        clk = 0;
        rst_active_high = 1;
        freq_word = 0;
    end

    // Test stimulus
    initial begin
        real clk_freq_hz = 1.0e9 / CLK_PERIOD; // Clock frequency in Hz
        int num_samples;
        int cycle_count;

        // Open file for plotting
        waveform_file_handle = $fopen("dds_sine_output.csv", "w");
        $fwrite(waveform_file_handle, "Time_ns,Sine_Out,Sine_Out_Normalized\n");

        // Wait for a few clocks
        repeat(10) @(posedge clk);
        rst_active_high = 0;
        @(posedge clk);

        $display("Clock Frequency: %.2f MHz", clk_freq_hz/1e6);
        $display("Phase Width: %0d bits", PHASE_WIDTH);
        $display("Data Width: %0d bits", DATA_WIDTH);
        $display("");

        // Test 1: Generate 1 MHz sine wave
        $display("Test 1: Generating 1 MHz sine wave");
        freq_word = calc_freq_word(1.0e6, clk_freq_hz);
        $display("Frequency: 1.000 MHz");
        $display("Frequency Word: 0x%08h (%0d)", freq_word, freq_word);
        $display("");
        num_samples = 1000; // Capture 10 cycles at 100 MHz clock
        cycle_count = 0;

        repeat(num_samples) begin
            @(posedge clk);
            $fwrite(waveform_file_handle, "%0t,%0d,%.6f\n", 
                    $time, sine_out, real'(sine_out)/32768.0);
            cycle_count++;
        end

        // Test 2: Generate 5 MHz sine wave
        $display("Test 2: Generating 5 MHz sine wave");
        freq_word = calc_freq_word(5.0e6, clk_freq_hz);
        $display("Frequency: 5.000 MHz");
        $display("Frequency Word: 0x%08h (%0d)", freq_word, freq_word);
        $display("");
        num_samples = 500; // Capture 25 cycles

        repeat(num_samples) begin
            @(posedge clk);
            $fwrite(waveform_file_handle, "%0t,%0d,%.6f\n", 
                    $time, sine_out, real'(sine_out)/32768.0);
        end

        // Test 3: Test reset functionality
        $display("Test 3: Testing Reset Functionality");
        freq_word = calc_freq_word(1.0e6, clk_freq_hz);
        repeat(50) @(posedge clk);

        rst_active_high = 1;
        @(posedge clk);
        if (sine_out === 0) begin
            $display("PASS: Output correctly reset to 0");
        end else begin
            $display("FAIL: Output not reset (value = %0d)", sine_out);
        end

        rst_active_high = 0;
        repeat(50) @(posedge clk);
        $display("");

        // Test 4: Sweep through multiple frequencies
        $display("Test 4: Frequency Sweep");
        for (int i = 1; i <= 5; i++) begin
            real test_freq = i * 2.0e6; // 2, 4, 6, 8, 10 MHz
            freq_word = calc_freq_word(test_freq, clk_freq_hz);
            $display("Frequency: %.2f MHz, Freq Word: 0x%08h", 
                     test_freq/1e6, freq_word);
            
            repeat(100) begin
                @(posedge clk);
                $fwrite(waveform_file_handle, "%0t,%0d,%.6f\n", 
                        $time, sine_out, real'(sine_out)/32768.0);
            end
        end
        $display("");

        // Close file and finish
        $fclose(waveform_file_handle);

        $display("Output saved to: dds_sine_output.csv");

        #100;
        $finish;
    end

    // Monitor for debugging
    initial begin
        $monitor("Time=%0t clk=%b rst=%b freq_word=%h sine_out=%d", 
                 $time, clk, rst_active_high, freq_word, sine_out);
    end

    // Waveform dump for viewing in waveform viewer
    initial begin
        $dumpfile("dds_sine_tb.vcd");
        $dumpvars(0, tb_DDS_Sine);
        #500000; // Run for 500us max
        $display("WARNING: Simulation timeout reached");
        $finish;
    end

endmodule

spartan_tracker/spartan_tracker.sim/sim_1/behav/xsim/dds_sine_tb.vcd
$date
   Fri Nov 21 02:56:38 2025
$end
$version
  2022.2
$end
$timescale
  1ps
$end
$scope module tb_DDS_Sine $end
$var reg 1 ! clk $end
$var reg 1 " rst_active_high $end
$var reg 32 # freq_word [31:0] $end
$var reg 16 $ sine_out [15:0] $end
$var reg 32 % waveform_file_handle [31:0] $end
$scope module dut $end
$var wire 1 & clk $end
$var wire 1 ' rst_active_high $end
$var wire 32 ( freq_word [31:0] $end
$var reg 16 $ sine_out [15:0] $end
$var reg 32 ) phase_acc_out [31:0] $end
$var reg 9 * lut_addr [8:0] $end
$var reg 16 + lut_data [15:0] $end
$scope module phase_acc_i $end
$var wire 1 & clk $end
$var wire 1 ' rst_active_high $end
$var wire 32 ( freq_control_word [31:0] $end
$var reg 32 ) phase_accumulator_out [31:0] $end
$var reg 32 , phase_accumulator_reg [31:0] $end
$upscope $end
$scope module SineLUT $end
$var wire 1 & clk $end
$var wire 9 - addr_full [8:0] $end
$var reg 16 + data_out [15:0] $end
$var reg 7 . addr_quarter [6:0] $end
$var reg 2 / quadrant [1:0] $end
$var reg 16 0 lut_val [15:0] $end
$var reg 1 1 sign_flip $end
$upscope $end
$upscope $end
$scope begin Block43_7 $end
$var real 32 2 clk_freq_hz $end
$var reg 32 3 num_samples [31:0] $end
$var reg 32 4 cycle_count [31:0] $end
$scope begin Block111_8 $end
$var reg 32 5 i [31:0] $end
$scope begin Block111_9 $end
$var real 32 6 test_freq $end
$upscope $end
$upscope $end
$upscope $end
$scope function calc_freq_word $end
$var reg 32 7 calc_freq_word [31:0] $end
$var real 32 8 desired_freq_hz $end
$var real 32 9 clk_freq_hz $end
$var real 32 : ratio $end
$upscope $end
$upscope $end
$enddefinitions $end
#0
$dumpvars
0!
1"
b0 #
b0 $
b11111111111111111011000111100000 %
0&
1'
b0 (
b0 )
b0 *
bx +
b0 ,
b0 -
b0 .
b0 /
b0 0
01
r100000000 2
b0 3
b0 4
b0 5
r0 6
b0 7
r0 8
r0 9
r5.449851975339438e-316 :
$end
#5000
1!
1&
b0 +
#10000
0!
0&
#15000
1!
1&
#20000
0!
0&
#25000
1!
1&
#30000
0!
0&
#35000
1!
1&
#40000
0!
0&
#45000
1!
1&
#50000
0!
0&
#55000
1!
1&
#60000
0!
0&
#65000
1!
1&
#70000
0!
0&
#75000
1!
1&
#80000
0!
0&
#85000
1!
1&
#90000
0!
0&
#95000
1!
0"
1&
0'
#100000
0!
0&
#105000
1!
b10100011110101110000101001 #
1&
b10100011110101110000101001 (
b10100011110101110000101001 )
b101 *
b10100011110101110000101001 ,
b101 -
b101 .
b11111011001 0
b1111101000 3
#110000
0!
0&
#115000
1!
1&
b101000111101011100001010010 )
b1010 *
b11111011001 +
b101000111101011100001010010 ,
b1010 -
b1010 .
b111110101011 0
b1 4
#120000
0!
0&
#125000
1!
b11111011001 $
1&
b111101011100001010001111011 )
b1111 *
b111110101011 +
b111101011100001010001111011 ,
b1111 -
b1111 .
b1011101101110 0
b10 4
#130000
0!
0&
#135000
1!
b111110101011 $
1&
b1010001111010111000010100100 )
b10100 *
b1011101101110 +
b1010001111010111000010100100 ,
b10100 -
b10100 .
b1111100011010 0
b11 4
#140000
0!
0&
#145000
1!
b1011101101110 $
1&
b1100110011001100110011001101 )
b11001 *
b1111100011010 +
b1100110011001100110011001101 ,
b11001 -
b11001 .
b10011010101000 0
b100 4
#150000
0!
0&
#155000
1!
b1111100011010 $
1&
b1111010111000010100011110110 )
b11110 *
b10011010101000 +
b1111010111000010100011110110 ,
b11110 -
b11110 .
b10111000010001 0
b101 4
#160000
0!
0&
#165000
1!
b10011010101000 $
1&
b10001111010111000010100011111 )
b100011 *
b10111000010001 +
b10001111010111000010100011111 ,
b100011 -
b100011 .
b11010101001101 0
b110 4
#170000
0!
0&
#175000
1!
b10111000010001 $
1&
b10100011110101110000101001000 )
b101000 *
b11010101001101 +
b10100011110101110000101001000 ,
b101000 -
b101000 .
b11110001010110 0
b111 4
#180000
0!
0&
#185000
1!
b11010101001101 $
1&
b10111000010100011110101110001 )
b101110 *
b11110001010110 +
b10111000010100011110101110001 ,
b101110 -
b101110 .
b100010001111010 0
b1000 4
#190000
0!
0&
#195000
1!
b11110001010110 $
1&
b11001100110011001100110011010 )
b110011 *
b100010001111010 +
b11001100110011001100110011010 ,
b110011 -
b110011 .
b100101011111011 0
b1001 4
#200000
0!
0&
#205000
1!
b100010001111010 $
1&
b11100001010001111010111000011 )
b111000 *
b100101011111011 +
b11100001010001111010111000011 ,
b111000 -
b111000 .
b101000100110011 0
b1010 4
#210000
0!
0&
#215000
1!
b100101011111011 $
1&
b11110101110000101000111101100 )
b111101 *
b101000100110011 +
b11110101110000101000111101100 ,
b111101 -
b111101 .
b101011100011101 0
b1011 4
#220000
0!
0&
#225000
1!
b101000100110011 $
1&
b100001010001111010111000010101 )
b1000010 *
b101011100011101 +
b100001010001111010111000010101 ,
b1000010 -
b1000010 .
b101110010110011 0
b1100 4
#230000
0!
0&
#235000
1!
b101011100011101 $
1&
b100011110101110000101000111110 )
b1000111 *
b101110010110011 +
b100011110101110000101000111110 ,
b1000111 -
b1000111 .
b110000111110000 0
b1101 4
#240000
0!
0&
#245000
1!
b101110010110011 $
1&
b100110011001100110011001100111 )
b1001100 *
b110000111110000 +
b100110011001100110011001100111 ,
b1001100 -
b1001100 .
b110011011001111 0
b1110 4
#250000
0!
0&
#255000
1!
b110000111110000 $
1&
b101000111101011100001010010000 )
b1010001 *
b110011011001111 +
b101000111101011100001010010000 ,
b1010001 -
b1010001 .
b110101101001010 0
b1111 4
#260000
0!
0&
#265000
1!
b110011011001111 $
1&
b101011100001010001111010111001 )
b1010111 *
b110101101001010 +
b101011100001010001111010111001 ,
b1010111 -
b1010111 .
b111000000100010 0
b10000 4
#270000
0!
0&
#275000
1!
b110101101001010 $
1&
b101110000101000111101011100010 )
b1011100 *
b111000000100010 +
b101110000101000111101011100010 ,
b1011100 -
b1011100 .
b111001110110101 0
b10001 4
#280000
0!
0&
#285000
1!
b111000000100010 $
1&
b110000101000111101011100001011 )
b1100001 *
b111001110110101 +
b110000101000111101011100001011 ,
b1100001 -
b1100001 .
b111011011011000 0
b10010 4
#290000
0!
0&
#295000
1!
b111001110110101 $
1&
b110011001100110011001100110100 )
b1100110 *
b111011011011000 +
b110011001100110011001100110100 ,
b1100110 -
b1100110 .
b111100110001001 0
b10011 4
#300000
0!
0&
#305000
1!
b111011011011000 $
1&
b110101110000101000111101011101 )
b1101011 *
b111100110001001 +
b110101110000101000111101011101 ,
b1101011 -
b1101011 .
b111101111000101 0
b10100 4
#310000
0!
0&
#315000
1!
b111100110001001 $
1&
b111000010100011110101110000110 )
b1110000 *
b111101111000101 +
b111000010100011110101110000110 ,
b1110000 -
b1110000 .
b111110110001001 0
b10101 4
#320000
0!
0&
#325000
1!
b111101111000101 $
1&
b111010111000010100011110101111 )
b1110101 *
b111110110001001 +
b111010111000010100011110101111 ,
b1110101 -
b1110101 .
b111111011010101 0
b10110 4
#330000
0!
0&
#335000
1!
b111110110001001 $
1&
b111101011100001010001111011000 )
b1111010 *
b111111011010101 +
b111101011100001010001111011000 ,
b1111010 -
b1111010 .
b111111110100110 0
b10111 4
#340000
0!
0&
#345000
1!
b111111011010101 $
1&
b1000000000000000000000000000001 )
b10000000 *
b111111110100110 +
b1000000000000000000000000000001 ,
b10000000 -
b1111111 .
b1 /
b111111111111101 0
b11000 4
#350000
0!
0&
#355000
1!
b111111110100110 $
1&
b1000010100011110101110000101010 )
b10000101 *
b111111111111101 +
b1000010100011110101110000101010 ,
b10000101 -
b1111010 .
b111111110100110 0
b11001 4
#360000
0!
0&
#365000
1!
b111111111111101 $
1&
b1000101000111101011100001010011 )
b10001010 *
b111111110100110 +
b1000101000111101011100001010011 ,
b10001010 -
b1110101 .
b111111011010101 0
b11010 4
#370000
0!
0&
#375000
1!
b111111110100110 $
1&
b1000111101011100001010001111100 )
b10001111 *
b111111011010101 +
b1000111101011100001010001111100 ,
b10001111 -
b1110000 .
b111110110001001 0
b11011 4
#380000
0!
0&
#385000
1!
b111111011010101 $
1&
b1001010001111010111000010100101 )
b10010100 *
b111110110001001 +
b1001010001111010111000010100101 ,
b10010100 -
b1101011 .
b111101111000101 0
b11100 4
#390000
0!
0&
#395000
1!
b111110110001001 $
1&
b1001100110011001100110011001110 )
b10011001 *
b111101111000101 +
b1001100110011001100110011001110 ,
b10011001 -
b1100110 .
b111100110001001 0
b11101 4
#400000
0!
0&
#405000
1!
b111101111000101 $
1&
b1001111010111000010100011110111 )
b10011110 *
b111100110001001 +
b1001111010111000010100011110111 ,
b10011110 -
b1100001 .
b111011011011000 0
b11110 4
#410000
0!
0&
#415000
1!
b111100110001001 $
1&
b1010001111010111000010100100000 )
b10100011 *
b111011011011000 +
b1010001111010111000010100100000 ,
b10100011 -
b1011100 .
b111001110110101 0
b11111 4
#420000
0!
0&
#425000
1!
b111011011011000 $
1&
b1010100011110101110000101001001 )
b10101000 *
b111001110110101 +
b1010100011110101110000101001001 ,
b10101000 -
b1010111 .
b111000000100010 0
b100000 4
#430000
0!
0&
#435000
1!
b111001110110101 $
1&
b1010111000010100011110101110010 )
b10101110 *
b111000000100010 +
b1010111000010100011110101110010 ,
b10101110 -
b1010001 .
b110101101001010 0
b100001 4
#440000
0!
0&
#445000
1!
b111000000100010 $
1&
b1011001100110011001100110011011 )
b10110011 *
b110101101001010 +
b1011001100110011001100110011011 ,
b10110011 -
b1001100 .
b110011011001111 0
b100010 4
#450000
0!
0&
#455000
1!
b110101101001010 $
1&
b1011100001010001111010111000100 )
b10111000 *
b110011011001111 +
b1011100001010001111010111000100 ,
b10111000 -
b1000111 .
b110000111110000 0
b100011 4
#460000
0!
0&
#465000
1!
b110011011001111 $
1&
b1011110101110000101000111101101 )
b10111101 *
b110000111110000 +
b1011110101110000101000111101101 ,
b10111101 -
b1000010 .
b101110010110011 0
b100100 4
#470000
0!
0&
#475000
1!
b110000111110000 $
1&
b1100001010001111010111000010110 )
b11000010 *
b101110010110011 +
b1100001010001111010111000010110 ,
b11000010 -
b111101 .
b101011100011101 0
b100101 4
#480000
0!
0&
#485000
1!
b101110010110011 $
1&
b1100011110101110000101000111111 )
b11000111 *
b101011100011101 +
b1100011110101110000101000111111 ,
b11000111 -
b111000 .
b101000100110011 0
b100110 4
#490000
0!
0&
#495000
1!
b101011100011101 $
1&
b1100110011001100110011001101000 )
b11001100 *
b101000100110011 +
b1100110011001100110011001101000 ,
b11001100 -
b110011 .
b100101011111011 0
b100111 4
#500000
0!
0&
#505000
1!
b101000100110011 $
1&
b1101000111101011100001010010001 )
b11010001 *
b100101011111011 +
b1101000111101011100001010010001 ,
b11010001 -
b101110 .
b100010001111010 0
b101000 4
#510000
0!
0&
#515000
1!
b100101011111011 $
1&
b1101011100001010001111010111010 )
b11010111 *
b100010001111010 +
b1101011100001010001111010111010 ,
b11010111 -
b101000 .
b11110001010110 0
b101001 4
#520000
0!
0&
#525000
1!
b100010001111010 $
1&
b1101110000101000111101011100011 )
b11011100 *
b11110001010110 +
b1101110000101000111101011100011 ,
b11011100 -
b100011 .
b11010101001101 0
b101010 4
#530000
0!
0&
#535000
1!
b11110001010110 $
1&
b1110000101000111101011100001100 )
b11100001 *
b11010101001101 +
b1110000101000111101011100001100 ,
b11100001 -
b11110 .
b10111000010001 0
b101011 4
#540000
0!
0&
#545000
1!
b11010101001101 $
1&
b1110011001100110011001100110101 )
b11100110 *
b10111000010001 +
b1110011001100110011001100110101 ,
b11100110 -
b11001 .
b10011010101000 0
b101100 4
#550000
0!
0&
#555000
1!
b10111000010001 $
1&
b1110101110000101000111101011110 )
b11101011 *
b10011010101000 +
b1110101110000101000111101011110 ,
b11101011 -
b10100 .
b1111100011010 0
b101101 4
#560000
0!
0&
#565000
1!
b10011010101000 $
1&
b1111000010100011110101110000111 )
b11110000 *
b1111100011010 +
b1111000010100011110101110000111 ,
b11110000 -
b1111 .
b1011101101110 0
b101110 4
#570000
0!
0&
#575000
1!
b1111100011010 $
1&
b1111010111000010100011110110000 )
b11110101 *
b1011101101110 +
b1111010111000010100011110110000 ,
b11110101 -
b1010 .
b111110101011 0
b101111 4
#580000
0!
0&
#585000
1!
b1011101101110 $
1&
b1111101011100001010001111011001 )
b11111010 *
b111110101011 +
b1111101011100001010001111011001 ,
b11111010 -
b101 .
b11111011001 0
b110000 4
#590000
0!
0&
#595000
1!
b111110101011 $
1&
b10000000000000000000000000000010 )
b100000000 *
b11111011001 +
b10000000000000000000000000000010 ,
b100000000 -
b0 .
b10 /
b0 0
11
b110001 4
#600000
0!
0&
#605000
1!
b11111011001 $
1&
b10000010100011110101110000101011 )
b100000101 *
b0 +
b10000010100011110101110000101011 ,
b100000101 -
b101 .
b11111011001 0
b110010 4
#610000
0!
0&
#615000
1!
b0 $
1&
b10000101000111101011100001010100 )
b100001010 *
b1111100000100111 +
b10000101000111101011100001010100 ,
b100001010 -
b1010 .
b111110101011 0
b110011 4
#620000
0!
0&
#625000
1!
b1111100000100111 $
1&
b10000111101011100001010001111101 )
b100001111 *
b1111000001010101 +
b10000111101011100001010001111101 ,
b100001111 -
b1111 .
b1011101101110 0
b110100 4
#630000
0!
0&
#635000
1!
b1111000001010101 $
1&
b10001010001111010111000010100110 )
b100010100 *
b1110100010010010 +
b10001010001111010111000010100110 ,
b100010100 -
b10100 .
b1111100011010 0
b110101 4
#640000
0!
0&
#645000
1!
b1110100010010010 $
1&
b10001100110011001100110011001111 )
b100011001 *
b1110000011100110 +
b10001100110011001100110011001111 ,
b100011001 -
b11001 .
b10011010101000 0
b110110 4
#650000
0!
0&
#655000
1!
b1110000011100110 $
1&
b10001111010111000010100011111000 )
b100011110 *
b1101100101011000 +
b10001111010111000010100011111000 ,
b100011110 -
b11110 .
b10111000010001 0
b110111 4
#660000
0!
0&
#665000
1!
b1101100101011000 $
1&
b10010001111010111000010100100001 )
b100100011 *
b1101000111101111 +
b10010001111010111000010100100001 ,
b100100011 -
b100011 .
b11010101001101 0
b111000 4
#670000
0!
0&
#675000
1!
b1101000111101111 $
1&
b10010100011110101110000101001010 )
b100101000 *
b1100101010110011 +
b10010100011110101110000101001010 ,
b100101000 -
b101000 .
b11110001010110 0
b111001 4
#680000
0!
0&
#685000
1!
b1100101010110011 $
1&
b10010111000010100011110101110011 )
b100101110 *
b1100001110101010 +
b10010111000010100011110101110011 ,
b100101110 -
b101110 .
b100010001111010 0
b111010 4
#690000
0!
0&
#695000
1!
b1100001110101010 $
1&
b10011001100110011001100110011100 )
b100110011 *
b1011101110000110 +
b10011001100110011001100110011100 ,
b100110011 -
b110011 .
b100101011111011 0
b111011 4
#700000
0!
0&
#705000
1!
b1011101110000110 $
1&
b10011100001010001111010111000101 )
b100111000 *
b1011010100000101 +
b10011100001010001111010111000101 ,
b100111000 -
b111000 .
b101000100110011 0
b111100 4
#710000
0!
0&
#715000
1!
b1011010100000101 $
1&
b10011110101110000101000111101110 )
b100111101 *
b1010111011001101 +
b10011110101110000101000111101110 ,
b100111101 -
b111101 .
b101011100011101 0
b111101 4
#720000
0!
0&
#725000
1!
b1010111011001101 $
1&
b10100001010001111010111000010111 )
b101000010 *
b1010100011100011 +
b10100001010001111010111000010111 ,
b101000010 -
b1000010 .
b101110010110011 0
b111110 4
#730000
0!
0&
#735000
1!
b1010100011100011 $
1&
b10100011110101110000101001000000 )
b101000111 *
b1010001101001101 +
b10100011110101110000101001000000 ,
b101000111 -
b1000111 .
b110000111110000 0
b111111 4
#740000
0!
0&
#745000
1!
b1010001101001101 $
1&
b10100110011001100110011001101001 )
b101001100 *
b1001111000010000 +
b10100110011001100110011001101001 ,
b101001100 -
b1001100 .
b110011011001111 0
b1000000 4
#750000
0!
0&
#755000
1!
b1001111000010000 $
1&
b10101000111101011100001010010010 )
b101010001 *
b1001100100110001 +
b10101000111101011100001010010010 ,
b101010001 -
b1010001 .
b110101101001010 0
b1000001 4
#760000
0!
0&
#765000
1!
b1001100100110001 $
1&
b10101011100001010001111010111011 )
b101010111 *
b1001010010110110 +
b10101011100001010001111010111011 ,
b101010111 -
b1010111 .
b111000000100010 0
b1000010 4
#770000
0!
0&
#775000
1!
b1001010010110110 $
1&
b10101110000101000111101011100100 )
b101011100 *
b1000111111011110 +
b10101110000101000111101011100100 ,
b101011100 -
b1011100 .
b111001110110101 0
b1000011 4
#780000
0!
0&
#785000
1!
b1000111111011110 $
1&
b10110000101000111101011100001101 )
b101100001 *
b1000110001001011 +
b10110000101000111101011100001101 ,
b101100001 -
b1100001 .
b111011011011000 0
b1000100 4
#790000
0!
0&
#795000
1!
b1000110001001011 $
1&
b10110011001100110011001100110110 )
b101100110 *
b1000100100101000 +
b10110011001100110011001100110110 ,
b101100110 -
b1100110 .
b111100110001001 0
b1000101 4
#800000
0!
0&
#805000
1!
b1000100100101000 $
1&
b10110101110000101000111101011111 )
b101101011 *
b1000011001110111 +
b10110101110000101000111101011111 ,
b101101011 -
b1101011 .
b111101111000101 0
b1000110 4
#810000
0!
0&
#815000
1!
b1000011001110111 $
1&
b10111000010100011110101110001000 )
b101110000 *
b1000010000111011 +
b10111000010100011110101110001000 ,
b101110000 -
b1110000 .
b111110110001001 0
b1000111 4
#820000
0!
0&
#825000
1!
b1000010000111011 $
1&
b10111010111000010100011110110001 )
b101110101 *
b1000001001110111 +
b10111010111000010100011110110001 ,
b101110101 -
b1110101 .
b111111011010101 0
b1001000 4
#830000
0!
0&
#835000
1!
b1000001001110111 $
1&
b10111101011100001010001111011010 )
b101111010 *
b1000000100101011 +
b10111101011100001010001111011010 ,
b101111010 -
b1111010 .
b111111110100110 0
b1001001 4
#840000
0!
0&
#845000
1!
b1000000100101011 $
1&
b11000000000000000000000000000011 )
b110000000 *
b1000000001011010 +
b11000000000000000000000000000011 ,
b110000000 -
b1111111 .
b11 /
b111111111111101 0
b1001010 4
#850000
0!
0&
#855000
1!
b1000000001011010 $
1&
b11000010100011110101110000101100 )
b110000101 *
b1000000000000011 +
b11000010100011110101110000101100 ,
b110000101 -
b1111010 .
b111111110100110 0
b1001011 4
#860000
0!
0&
#865000
1!
b1000000000000011 $
1&
b11000101000111101011100001010101 )
b110001010 *
b1000000001011010 +
b11000101000111101011100001010101 ,
b110001010 -
b1110101 .
b111111011010101 0
b1001100 4
#870000
0!
0&
#875000
1!
b1000000001011010 $
1&
b11000111101011100001010001111110 )
b110001111 *
b1000000100101011 +
b11000111101011100001010001111110 ,
b110001111 -
b1110000 .
b111110110001001 0
b1001101 4
#880000
0!
0&
#885000
1!
b1000000100101011 $
1&
b11001010001111010111000010100111 )
b110010100 *
b1000001001110111 +
b11001010001111010111000010100111 ,
b110010100 -
b1101011 .
b111101111000101 0
b1001110 4
#890000
0!
0&
#895000
1!
b1000001001110111 $
1&
b11001100110011001100110011010000 )
b110011001 *
b1000010000111011 +
b11001100110011001100110011010000 ,
b110011001 -
b1100110 .
b111100110001001 0
b1001111 4
#900000
0!
0&
#905000
1!
b1000010000111011 $
1&
b11001111010111000010100011111001 )
b110011110 *
b1000011001110111 +
b11001111010111000010100011111001 ,
b110011110 -
b1100001 .
b111011011011000 0
b1010000 4
#910000
0!
0&
#915000
1!
b1000011001110111 $
1&
b11010001111010111000010100100010 )
b110100011 *
b1000100100101000 +
b11010001111010111000010100100010 ,
b110100011 -
b1011100 .
b111001110110101 0
b1010001 4
#920000
0!
0&
#925000
1!
b1000100100101000 $
1&
b11010100011110101110000101001011 )
b110101000 *
b1000110001001011 +
b11010100011110101110000101001011 ,
b110101000 -
b1010111 .
b111000000100010 0
b1010010 4
#930000
0!
0&
#935000
1!
b1000110001001011 $
1&
b11010111000010100011110101110100 )
b110101110 *
b1000111111011110 +
b11010111000010100011110101110100 ,
b110101110 -
b1010001 .
b110101101001010 0
b1010011 4
#940000
0!
0&
#945000
1!
b1000111111011110 $
1&
b11011001100110011001100110011101 )
b110110011 *
b1001010010110110 +
b11011001100110011001100110011101 ,
b110110011 -
b1001100 .
b110011011001111 0
b1010100 4
#950000
0!
0&
